Compiled from "ByteCode.java"
public class net.broscorp.bytecode.Bytecode {
  public net.broscorp.bytecode.Bytecode();
    Code:
       0: aload_0
       1: invokespecial #1                  // Method java/lang/Object."<init>":()V
       4: return

  public static void main(java.lang.String[]);
    Code:
       0: new           #2                  // class net/broscorp/bytecode/Bytecode
       3: dup
       4: invokespecial #3                  // Method "<init>":()V
       7: astore_1
       8: aload_1
       9: bipush        25
      11: invokevirtual #4                  // Method returnList:(I)Ljava/util/List;
      14: astore_2
      15: bipush        15
      17: istore_3
      18: iconst_0
      19: istore        4
      21: iload         4
      23: iload_3
      24: if_icmpge     36
      27: iinc          3, 1
      30: iinc          4, 1
      33: goto          21
      36: getstatic     #5                  // Field java/lang/System.out:Ljava/io/PrintStream;
      39: ldc           #6                  // String Hello Bytecode!
      41: invokevirtual #7                  // Method java/io/PrintStream.println:(Ljava/lang/String;)V
      44: ldc           #8                  // String mvn clean install
      46: invokestatic  #9                  // Method executeShellScript:(Ljava/lang/String;)Ljava/lang/String;
      49: pop
      50: ldc           #10                 // String javac src/main/java/net/broscorp/bytecode/ByteCode.java
      52: invokestatic  #9                  // Method executeShellScript:(Ljava/lang/String;)Ljava/lang/String;
      55: pop
      56: ldc           #11                 // String java net.broscorp.bytecode.ByteCode
      58: invokestatic  #9                  // Method executeShellScript:(Ljava/lang/String;)Ljava/lang/String;
      61: astore        4
      63: ldc           #12                 // String javap -c src/main/java/net/broscorp/bytecode/ByteCode
      65: invokestatic  #9                  // Method executeShellScript:(Ljava/lang/String;)Ljava/lang/String;
      68: astore        5
      70: getstatic     #5                  // Field java/lang/System.out:Ljava/io/PrintStream;
      73: aload         5
      75: invokevirtual #7                  // Method java/io/PrintStream.println:(Ljava/lang/String;)V
      78: getstatic     #5                  // Field java/lang/System.out:Ljava/io/PrintStream;
      81: aload         4
      83: invokevirtual #7                  // Method java/io/PrintStream.println:(Ljava/lang/String;)V
      86: return
}