// class version 52.0 (52)
// access flags 0x21
public class net/broscorp/bytecode/Main {

  // compiled from: Main.java

  // access flags 0x1
  public <init>()V
   L0
    LINENUMBER 5 L0
    ALOAD 0
    INVOKESPECIAL java/lang/Object.<init> ()V                                      //Call method java/lang/Object.<init> ()V
    RETURN
   L1
    LOCALVARIABLE this Lnet/broscorp/bytecode/Main; L0 L1 0
    MAXSTACK = 1
    MAXLOCALS = 1

  // access flags 0x9
  public static main([Ljava/lang/String;)V
   L0
    LINENUMBER 8 L0
    ICONST_2                                                                       //i = 2
    ISTORE 1
   L1
    LINENUMBER 9 L1
   FRAME APPEND [I]
    ILOAD 1
    IINC 1 1                                                                       //increase i in steps of 1
    BIPUSH 8                                                                       //max value for condition
    IF_ICMPGE L2                                                                   //if i => 20 go to L2 mark
   L3
    LINENUMBER 10 L3
    GETSTATIC java/lang/System.out : Ljava/io/PrintStream;
    NEW java/lang/StringBuilder                                                    //create StringBuilder()
    DUP
    INVOKESPECIAL java/lang/StringBuilder.<init> ()V
    LDC "i = "                                                                     //print "i = "
    INVOKEVIRTUAL java/lang/StringBuilder.append (Ljava/lang/String;)Ljava/lang/StringBuilder;
    ILOAD 1
    INVOKEVIRTUAL java/lang/StringBuilder.append (I)Ljava/lang/StringBuilder;       //append i value to StringBuilder
    INVOKEVIRTUAL java/lang/StringBuilder.toString ()Ljava/lang/String;             //convert StringBuilder to String
    INVOKEVIRTUAL java/io/PrintStream.println (Ljava/lang/String;)V                 //print current value i
    GOTO L1                                                                         //return to L1 mark
   L2
    LINENUMBER 13 L2
   FRAME SAME
    SIPUSH 5545                                                                     //i = 5545
    INVOKESTATIC net/broscorp/bytecode/Main.print (I)I                              //call method print with var = i;
    ISTORE 1
   L4
    LINENUMBER 15 L4
    GETSTATIC java/lang/System.out : Ljava/io/PrintStream;
    NEW java/lang/StringBuilder                                                     //create StringBuilder()
    DUP
    INVOKESPECIAL java/lang/StringBuilder.<init> ()V
    LDC "new i = "                                                                  //print "new i = "
    INVOKEVIRTUAL java/lang/StringBuilder.append (Ljava/lang/String;)Ljava/lang/StringBuilder;
    ILOAD 1
    INVOKEVIRTUAL java/lang/StringBuilder.append (I)Ljava/lang/StringBuilder;       //append i value to StringBuilder
    INVOKEVIRTUAL java/lang/StringBuilder.toString ()Ljava/lang/String;             //convert StringBuilder to String
    INVOKEVIRTUAL java/io/PrintStream.println (Ljava/lang/String;)V                 //print new value i = 5555
   L5
    LINENUMBER 16 L5
    GETSTATIC java/lang/System.out : Ljava/io/PrintStream;
    LDC "Hello World! by Nikita"                                                    //print "Hello World! by Nikita"
    INVOKEVIRTUAL java/io/PrintStream.println (Ljava/lang/String;)V
   L6
    LINENUMBER 17 L6
    RETURN                                                                          //end program
   L7
    LOCALVARIABLE args [Ljava/lang/String; L0 L7 0
    LOCALVARIABLE i I L1 L7 1
    MAXSTACK = 3
    MAXLOCALS = 2

  // access flags 0x9
  public static print(I)I
   L0
    LINENUMBER 20 L0
    IINC 0 10                                                                     //increase tmp by 10
   L1
    LINENUMBER 21 L1
    ILOAD 0
    IRETURN                                                                       //return tmp value
   L2
    LOCALVARIABLE tmp I L0 L2 0
    MAXSTACK = 1
    MAXLOCALS = 1
}
